{
  "id": "e6180b2c-6668-4ef5-94d4-ebd24f1ce8d0",
  "prevId": "b5b94eb4-c4fd-4eb1-a786-46e5db711d90",
  "version": "7",
  "dialect": "postgresql",
  "tables": {
    "public.categoria_productos": {
      "name": "categoria_productos",
      "schema": "",
      "columns": {
        "id": {
          "name": "id",
          "type": "integer",
          "primaryKey": true,
          "notNull": true,
          "identity": {
            "type": "always",
            "name": "categoria_productos_id_seq",
            "schema": "public",
            "increment": "1",
            "startWith": "1",
            "minValue": "1",
            "maxValue": "2147483647",
            "cache": "1",
            "cycle": false
          }
        },
        "categoria": {
          "name": "categoria",
          "type": "text",
          "primaryKey": false,
          "notNull": true
        }
      },
      "indexes": {},
      "foreignKeys": {},
      "compositePrimaryKeys": {},
      "uniqueConstraints": {},
      "policies": {},
      "checkConstraints": {},
      "isRLSEnabled": false
    },
    "public.departamentos": {
      "name": "departamentos",
      "schema": "",
      "columns": {
        "id": {
          "name": "id",
          "type": "integer",
          "primaryKey": true,
          "notNull": true,
          "identity": {
            "type": "always",
            "name": "departamentos_id_seq",
            "schema": "public",
            "increment": "1",
            "startWith": "1",
            "minValue": "1",
            "maxValue": "2147483647",
            "cache": "1",
            "cycle": false
          }
        },
        "departamento": {
          "name": "departamento",
          "type": "text",
          "primaryKey": false,
          "notNull": true
        }
      },
      "indexes": {},
      "foreignKeys": {},
      "compositePrimaryKeys": {},
      "uniqueConstraints": {},
      "policies": {},
      "checkConstraints": {},
      "isRLSEnabled": false
    },
    "public.entidades_academicas": {
      "name": "entidades_academicas",
      "schema": "",
      "columns": {
        "id": {
          "name": "id",
          "type": "integer",
          "primaryKey": true,
          "notNull": true,
          "identity": {
            "type": "always",
            "name": "entidades_academicas_id_seq",
            "schema": "public",
            "increment": "1",
            "startWith": "1",
            "minValue": "1",
            "maxValue": "2147483647",
            "cache": "1",
            "cycle": false
          }
        },
        "nombre": {
          "name": "nombre",
          "type": "text",
          "primaryKey": false,
          "notNull": true
        },
        "tipo": {
          "name": "tipo",
          "type": "text",
          "primaryKey": false,
          "notNull": true
        },
        "abreviacion": {
          "name": "abreviacion",
          "type": "text",
          "primaryKey": false,
          "notNull": true
        }
      },
      "indexes": {},
      "foreignKeys": {},
      "compositePrimaryKeys": {},
      "uniqueConstraints": {},
      "policies": {},
      "checkConstraints": {},
      "isRLSEnabled": false
    },
    "public.ordenes_detalle": {
      "name": "ordenes_detalle",
      "schema": "",
      "columns": {
        "id": {
          "name": "id",
          "type": "integer",
          "primaryKey": true,
          "notNull": true,
          "identity": {
            "type": "always",
            "name": "ordenes_detalle_id_seq",
            "schema": "public",
            "increment": "1",
            "startWith": "1",
            "minValue": "1",
            "maxValue": "2147483647",
            "cache": "1",
            "cycle": false
          }
        },
        "id_orden": {
          "name": "id_orden",
          "type": "integer",
          "primaryKey": false,
          "notNull": true
        },
        "id_solicitud_detalle": {
          "name": "id_solicitud_detalle",
          "type": "integer",
          "primaryKey": false,
          "notNull": true
        },
        "cantidad": {
          "name": "cantidad",
          "type": "real",
          "primaryKey": false,
          "notNull": true
        },
        "precio_real": {
          "name": "precio_real",
          "type": "real",
          "primaryKey": false,
          "notNull": false
        }
      },
      "indexes": {},
      "foreignKeys": {
        "ordenes_detalle_id_orden_ordenes_id_fk": {
          "name": "ordenes_detalle_id_orden_ordenes_id_fk",
          "tableFrom": "ordenes_detalle",
          "tableTo": "ordenes",
          "columnsFrom": [
            "id_orden"
          ],
          "columnsTo": [
            "id"
          ],
          "onDelete": "no action",
          "onUpdate": "no action"
        },
        "ordenes_detalle_id_solicitud_detalle_solicitudes_detalle_id_fk": {
          "name": "ordenes_detalle_id_solicitud_detalle_solicitudes_detalle_id_fk",
          "tableFrom": "ordenes_detalle",
          "tableTo": "solicitudes_detalle",
          "columnsFrom": [
            "id_solicitud_detalle"
          ],
          "columnsTo": [
            "id"
          ],
          "onDelete": "no action",
          "onUpdate": "no action"
        }
      },
      "compositePrimaryKeys": {},
      "uniqueConstraints": {},
      "policies": {},
      "checkConstraints": {},
      "isRLSEnabled": false
    },
    "public.ordenes_estados": {
      "name": "ordenes_estados",
      "schema": "",
      "columns": {
        "id": {
          "name": "id",
          "type": "integer",
          "primaryKey": true,
          "notNull": true,
          "identity": {
            "type": "always",
            "name": "ordenes_estados_id_seq",
            "schema": "public",
            "increment": "1",
            "startWith": "1",
            "minValue": "1",
            "maxValue": "2147483647",
            "cache": "1",
            "cycle": false
          }
        },
        "estado": {
          "name": "estado",
          "type": "text",
          "primaryKey": false,
          "notNull": true
        }
      },
      "indexes": {},
      "foreignKeys": {},
      "compositePrimaryKeys": {},
      "uniqueConstraints": {},
      "policies": {},
      "checkConstraints": {},
      "isRLSEnabled": false
    },
    "public.ordenes": {
      "name": "ordenes",
      "schema": "",
      "columns": {
        "id": {
          "name": "id",
          "type": "integer",
          "primaryKey": true,
          "notNull": true,
          "identity": {
            "type": "always",
            "name": "ordenes_id_seq",
            "schema": "public",
            "increment": "1",
            "startWith": "1",
            "minValue": "1",
            "maxValue": "2147483647",
            "cache": "1",
            "cycle": false
          }
        },
        "id_solicitud": {
          "name": "id_solicitud",
          "type": "integer",
          "primaryKey": false,
          "notNull": true
        },
        "fecha_creacion": {
          "name": "fecha_creacion",
          "type": "date",
          "primaryKey": false,
          "notNull": true
        },
        "fecha_a_utilizar": {
          "name": "fecha_a_utilizar",
          "type": "date",
          "primaryKey": false,
          "notNull": false
        },
        "id_proveedor": {
          "name": "id_proveedor",
          "type": "integer",
          "primaryKey": false,
          "notNull": false
        },
        "id_estado": {
          "name": "id_estado",
          "type": "integer",
          "primaryKey": false,
          "notNull": false
        },
        "numero_cotizacion": {
          "name": "numero_cotizacion",
          "type": "text",
          "primaryKey": false,
          "notNull": false
        },
        "termino_de_pago": {
          "name": "termino_de_pago",
          "type": "text",
          "primaryKey": false,
          "notNull": false
        },
        "moneda": {
          "name": "moneda",
          "type": "text",
          "primaryKey": false,
          "notNull": false
        },
        "observaciones": {
          "name": "observaciones",
          "type": "text",
          "primaryKey": false,
          "notNull": false
        }
      },
      "indexes": {},
      "foreignKeys": {
        "ordenes_id_solicitud_solicitudes_id_fk": {
          "name": "ordenes_id_solicitud_solicitudes_id_fk",
          "tableFrom": "ordenes",
          "tableTo": "solicitudes",
          "columnsFrom": [
            "id_solicitud"
          ],
          "columnsTo": [
            "id"
          ],
          "onDelete": "no action",
          "onUpdate": "no action"
        },
        "ordenes_id_proveedor_proveedores_id_fk": {
          "name": "ordenes_id_proveedor_proveedores_id_fk",
          "tableFrom": "ordenes",
          "tableTo": "proveedores",
          "columnsFrom": [
            "id_proveedor"
          ],
          "columnsTo": [
            "id"
          ],
          "onDelete": "no action",
          "onUpdate": "no action"
        },
        "ordenes_id_estado_ordenes_estados_id_fk": {
          "name": "ordenes_id_estado_ordenes_estados_id_fk",
          "tableFrom": "ordenes",
          "tableTo": "ordenes_estados",
          "columnsFrom": [
            "id_estado"
          ],
          "columnsTo": [
            "id"
          ],
          "onDelete": "no action",
          "onUpdate": "no action"
        }
      },
      "compositePrimaryKeys": {},
      "uniqueConstraints": {},
      "policies": {},
      "checkConstraints": {},
      "isRLSEnabled": false
    },
    "public.proveedores": {
      "name": "proveedores",
      "schema": "",
      "columns": {
        "id": {
          "name": "id",
          "type": "integer",
          "primaryKey": true,
          "notNull": true,
          "identity": {
            "type": "always",
            "name": "proveedores_id_seq",
            "schema": "public",
            "increment": "1",
            "startWith": "1",
            "minValue": "1",
            "maxValue": "2147483647",
            "cache": "1",
            "cycle": false
          }
        },
        "nombre_comercial": {
          "name": "nombre_comercial",
          "type": "text",
          "primaryKey": false,
          "notNull": true
        },
        "razon_social": {
          "name": "razon_social",
          "type": "text",
          "primaryKey": false,
          "notNull": false
        },
        "ruc": {
          "name": "ruc",
          "type": "text",
          "primaryKey": false,
          "notNull": false
        },
        "contacto_principal": {
          "name": "contacto_principal",
          "type": "text",
          "primaryKey": false,
          "notNull": false
        },
        "telefono": {
          "name": "telefono",
          "type": "text",
          "primaryKey": false,
          "notNull": false
        },
        "correo": {
          "name": "correo",
          "type": "text",
          "primaryKey": false,
          "notNull": false
        },
        "id_departamento": {
          "name": "id_departamento",
          "type": "integer",
          "primaryKey": false,
          "notNull": true
        },
        "direccion": {
          "name": "direccion",
          "type": "text",
          "primaryKey": false,
          "notNull": false
        },
        "id_sector": {
          "name": "id_sector",
          "type": "integer",
          "primaryKey": false,
          "notNull": false
        },
        "id_subsector": {
          "name": "id_subsector",
          "type": "integer",
          "primaryKey": false,
          "notNull": false
        }
      },
      "indexes": {},
      "foreignKeys": {
        "proveedores_id_departamento_departamentos_id_fk": {
          "name": "proveedores_id_departamento_departamentos_id_fk",
          "tableFrom": "proveedores",
          "tableTo": "departamentos",
          "columnsFrom": [
            "id_departamento"
          ],
          "columnsTo": [
            "id"
          ],
          "onDelete": "no action",
          "onUpdate": "no action"
        },
        "proveedores_id_sector_sectores_id_fk": {
          "name": "proveedores_id_sector_sectores_id_fk",
          "tableFrom": "proveedores",
          "tableTo": "sectores",
          "columnsFrom": [
            "id_sector"
          ],
          "columnsTo": [
            "id"
          ],
          "onDelete": "no action",
          "onUpdate": "no action"
        },
        "proveedores_id_subsector_subsectores_id_fk": {
          "name": "proveedores_id_subsector_subsectores_id_fk",
          "tableFrom": "proveedores",
          "tableTo": "subsectores",
          "columnsFrom": [
            "id_subsector"
          ],
          "columnsTo": [
            "id"
          ],
          "onDelete": "no action",
          "onUpdate": "no action"
        }
      },
      "compositePrimaryKeys": {},
      "uniqueConstraints": {},
      "policies": {},
      "checkConstraints": {},
      "isRLSEnabled": false
    },
    "public.sectores": {
      "name": "sectores",
      "schema": "",
      "columns": {
        "id": {
          "name": "id",
          "type": "integer",
          "primaryKey": true,
          "notNull": true,
          "identity": {
            "type": "always",
            "name": "sectores_id_seq",
            "schema": "public",
            "increment": "1",
            "startWith": "1",
            "minValue": "1",
            "maxValue": "2147483647",
            "cache": "1",
            "cycle": false
          }
        },
        "sector": {
          "name": "sector",
          "type": "text",
          "primaryKey": false,
          "notNull": true
        }
      },
      "indexes": {},
      "foreignKeys": {},
      "compositePrimaryKeys": {},
      "uniqueConstraints": {},
      "policies": {},
      "checkConstraints": {},
      "isRLSEnabled": false
    },
    "public.solicitudes_detalle": {
      "name": "solicitudes_detalle",
      "schema": "",
      "columns": {
        "id": {
          "name": "id",
          "type": "integer",
          "primaryKey": true,
          "notNull": true,
          "identity": {
            "type": "always",
            "name": "solicitudes_detalle_id_seq",
            "schema": "public",
            "increment": "1",
            "startWith": "1",
            "minValue": "1",
            "maxValue": "2147483647",
            "cache": "1",
            "cycle": false
          }
        },
        "id_solicitud": {
          "name": "id_solicitud",
          "type": "integer",
          "primaryKey": false,
          "notNull": true
        },
        "producto_servicio": {
          "name": "producto_servicio",
          "type": "text",
          "primaryKey": false,
          "notNull": true
        },
        "cantidad": {
          "name": "cantidad",
          "type": "real",
          "primaryKey": false,
          "notNull": true
        },
        "id_unidad_medida": {
          "name": "id_unidad_medida",
          "type": "integer",
          "primaryKey": false,
          "notNull": true
        },
        "precio": {
          "name": "precio",
          "type": "real",
          "primaryKey": false,
          "notNull": true
        },
        "observaciones": {
          "name": "observaciones",
          "type": "text",
          "primaryKey": false,
          "notNull": false
        },
        "prioridad": {
          "name": "prioridad",
          "type": "text",
          "primaryKey": false,
          "notNull": false
        },
        "id_estado": {
          "name": "id_estado",
          "type": "integer",
          "primaryKey": false,
          "notNull": false
        },
        "comprado": {
          "name": "comprado",
          "type": "real",
          "primaryKey": false,
          "notNull": false
        },
        "recibido": {
          "name": "recibido",
          "type": "real",
          "primaryKey": false,
          "notNull": false
        },
        "precio_compra": {
          "name": "precio_compra",
          "type": "real",
          "primaryKey": false,
          "notNull": false
        },
        "entrega_bodega": {
          "name": "entrega_bodega",
          "type": "real",
          "primaryKey": false,
          "notNull": false
        },
        "precio_bodega": {
          "name": "precio_bodega",
          "type": "real",
          "primaryKey": false,
          "notNull": false
        },
        "id_ubicacion": {
          "name": "id_ubicacion",
          "type": "integer",
          "primaryKey": false,
          "notNull": false
        },
        "id_categoria": {
          "name": "id_categoria",
          "type": "integer",
          "primaryKey": false,
          "notNull": false
        }
      },
      "indexes": {},
      "foreignKeys": {
        "solicitudes_detalle_id_solicitud_solicitudes_id_fk": {
          "name": "solicitudes_detalle_id_solicitud_solicitudes_id_fk",
          "tableFrom": "solicitudes_detalle",
          "tableTo": "solicitudes",
          "columnsFrom": [
            "id_solicitud"
          ],
          "columnsTo": [
            "id"
          ],
          "onDelete": "no action",
          "onUpdate": "no action"
        },
        "solicitudes_detalle_id_unidad_medida_unidades_medida_id_fk": {
          "name": "solicitudes_detalle_id_unidad_medida_unidades_medida_id_fk",
          "tableFrom": "solicitudes_detalle",
          "tableTo": "unidades_medida",
          "columnsFrom": [
            "id_unidad_medida"
          ],
          "columnsTo": [
            "id"
          ],
          "onDelete": "no action",
          "onUpdate": "no action"
        },
        "solicitudes_detalle_id_estado_solicitudes_estados_id_fk": {
          "name": "solicitudes_detalle_id_estado_solicitudes_estados_id_fk",
          "tableFrom": "solicitudes_detalle",
          "tableTo": "solicitudes_estados",
          "columnsFrom": [
            "id_estado"
          ],
          "columnsTo": [
            "id"
          ],
          "onDelete": "no action",
          "onUpdate": "no action"
        },
        "solicitudes_detalle_id_ubicacion_ubicaciones_id_fk": {
          "name": "solicitudes_detalle_id_ubicacion_ubicaciones_id_fk",
          "tableFrom": "solicitudes_detalle",
          "tableTo": "ubicaciones",
          "columnsFrom": [
            "id_ubicacion"
          ],
          "columnsTo": [
            "id"
          ],
          "onDelete": "no action",
          "onUpdate": "no action"
        },
        "solicitudes_detalle_id_categoria_categoria_productos_id_fk": {
          "name": "solicitudes_detalle_id_categoria_categoria_productos_id_fk",
          "tableFrom": "solicitudes_detalle",
          "tableTo": "categoria_productos",
          "columnsFrom": [
            "id_categoria"
          ],
          "columnsTo": [
            "id"
          ],
          "onDelete": "no action",
          "onUpdate": "no action"
        }
      },
      "compositePrimaryKeys": {},
      "uniqueConstraints": {},
      "policies": {},
      "checkConstraints": {},
      "isRLSEnabled": false
    },
    "public.solicitudes_estados": {
      "name": "solicitudes_estados",
      "schema": "",
      "columns": {
        "id": {
          "name": "id",
          "type": "integer",
          "primaryKey": true,
          "notNull": true,
          "identity": {
            "type": "always",
            "name": "solicitudes_estados_id_seq",
            "schema": "public",
            "increment": "1",
            "startWith": "1",
            "minValue": "1",
            "maxValue": "2147483647",
            "cache": "1",
            "cycle": false
          }
        },
        "estado": {
          "name": "estado",
          "type": "text",
          "primaryKey": false,
          "notNull": true
        }
      },
      "indexes": {},
      "foreignKeys": {},
      "compositePrimaryKeys": {},
      "uniqueConstraints": {},
      "policies": {},
      "checkConstraints": {},
      "isRLSEnabled": false
    },
    "public.solicitudes": {
      "name": "solicitudes",
      "schema": "",
      "columns": {
        "id": {
          "name": "id",
          "type": "integer",
          "primaryKey": true,
          "notNull": true,
          "identity": {
            "type": "always",
            "name": "solicitudes_id_seq",
            "schema": "public",
            "increment": "1",
            "startWith": "1",
            "minValue": "1",
            "maxValue": "2147483647",
            "cache": "1",
            "cycle": false
          }
        },
        "fecha": {
          "name": "fecha",
          "type": "date",
          "primaryKey": false,
          "notNull": true
        },
        "year": {
          "name": "year",
          "type": "integer",
          "primaryKey": false,
          "notNull": true
        },
        "id_entidad_academica": {
          "name": "id_entidad_academica",
          "type": "integer",
          "primaryKey": false,
          "notNull": true
        },
        "id_usuario": {
          "name": "id_usuario",
          "type": "integer",
          "primaryKey": false,
          "notNull": true
        },
        "revisado_bodega": {
          "name": "revisado_bodega",
          "type": "boolean",
          "primaryKey": false,
          "notNull": false
        }
      },
      "indexes": {},
      "foreignKeys": {
        "solicitudes_id_entidad_academica_entidades_academicas_id_fk": {
          "name": "solicitudes_id_entidad_academica_entidades_academicas_id_fk",
          "tableFrom": "solicitudes",
          "tableTo": "entidades_academicas",
          "columnsFrom": [
            "id_entidad_academica"
          ],
          "columnsTo": [
            "id"
          ],
          "onDelete": "no action",
          "onUpdate": "no action"
        },
        "solicitudes_id_usuario_usuarios_id_fk": {
          "name": "solicitudes_id_usuario_usuarios_id_fk",
          "tableFrom": "solicitudes",
          "tableTo": "usuarios",
          "columnsFrom": [
            "id_usuario"
          ],
          "columnsTo": [
            "id"
          ],
          "onDelete": "no action",
          "onUpdate": "no action"
        }
      },
      "compositePrimaryKeys": {},
      "uniqueConstraints": {},
      "policies": {},
      "checkConstraints": {},
      "isRLSEnabled": false
    },
    "public.solvencias": {
      "name": "solvencias",
      "schema": "",
      "columns": {
        "id": {
          "name": "id",
          "type": "integer",
          "primaryKey": true,
          "notNull": true,
          "identity": {
            "type": "always",
            "name": "solvencias_id_seq",
            "schema": "public",
            "increment": "1",
            "startWith": "1",
            "minValue": "1",
            "maxValue": "2147483647",
            "cache": "1",
            "cycle": false
          }
        },
        "id_proveedor": {
          "name": "id_proveedor",
          "type": "integer",
          "primaryKey": false,
          "notNull": true
        },
        "emitida": {
          "name": "emitida",
          "type": "date",
          "primaryKey": false,
          "notNull": false
        },
        "vence": {
          "name": "vence",
          "type": "date",
          "primaryKey": false,
          "notNull": false
        },
        "verificado": {
          "name": "verificado",
          "type": "date",
          "primaryKey": false,
          "notNull": true
        },
        "recibido": {
          "name": "recibido",
          "type": "date",
          "primaryKey": false,
          "notNull": false
        },
        "url": {
          "name": "url",
          "type": "text",
          "primaryKey": false,
          "notNull": false
        },
        "id_usuario": {
          "name": "id_usuario",
          "type": "integer",
          "primaryKey": false,
          "notNull": true
        }
      },
      "indexes": {},
      "foreignKeys": {
        "solvencias_id_proveedor_proveedores_id_fk": {
          "name": "solvencias_id_proveedor_proveedores_id_fk",
          "tableFrom": "solvencias",
          "tableTo": "proveedores",
          "columnsFrom": [
            "id_proveedor"
          ],
          "columnsTo": [
            "id"
          ],
          "onDelete": "no action",
          "onUpdate": "no action"
        },
        "solvencias_id_usuario_usuarios_id_fk": {
          "name": "solvencias_id_usuario_usuarios_id_fk",
          "tableFrom": "solvencias",
          "tableTo": "usuarios",
          "columnsFrom": [
            "id_usuario"
          ],
          "columnsTo": [
            "id"
          ],
          "onDelete": "no action",
          "onUpdate": "no action"
        }
      },
      "compositePrimaryKeys": {},
      "uniqueConstraints": {},
      "policies": {},
      "checkConstraints": {},
      "isRLSEnabled": false
    },
    "public.subsectores": {
      "name": "subsectores",
      "schema": "",
      "columns": {
        "id": {
          "name": "id",
          "type": "integer",
          "primaryKey": true,
          "notNull": true,
          "identity": {
            "type": "always",
            "name": "subsectores_id_seq",
            "schema": "public",
            "increment": "1",
            "startWith": "1",
            "minValue": "1",
            "maxValue": "2147483647",
            "cache": "1",
            "cycle": false
          }
        },
        "subsector": {
          "name": "subsector",
          "type": "text",
          "primaryKey": false,
          "notNull": true
        },
        "id_sector": {
          "name": "id_sector",
          "type": "integer",
          "primaryKey": false,
          "notNull": true
        }
      },
      "indexes": {},
      "foreignKeys": {
        "subsectores_id_sector_sectores_id_fk": {
          "name": "subsectores_id_sector_sectores_id_fk",
          "tableFrom": "subsectores",
          "tableTo": "sectores",
          "columnsFrom": [
            "id_sector"
          ],
          "columnsTo": [
            "id"
          ],
          "onDelete": "no action",
          "onUpdate": "no action"
        }
      },
      "compositePrimaryKeys": {},
      "uniqueConstraints": {},
      "policies": {},
      "checkConstraints": {},
      "isRLSEnabled": false
    },
    "public.ubicaciones": {
      "name": "ubicaciones",
      "schema": "",
      "columns": {
        "id": {
          "name": "id",
          "type": "integer",
          "primaryKey": true,
          "notNull": true,
          "identity": {
            "type": "always",
            "name": "ubicaciones_id_seq",
            "schema": "public",
            "increment": "1",
            "startWith": "1",
            "minValue": "1",
            "maxValue": "2147483647",
            "cache": "1",
            "cycle": false
          }
        },
        "ubicacion": {
          "name": "ubicacion",
          "type": "text",
          "primaryKey": false,
          "notNull": true
        }
      },
      "indexes": {},
      "foreignKeys": {},
      "compositePrimaryKeys": {},
      "uniqueConstraints": {},
      "policies": {},
      "checkConstraints": {},
      "isRLSEnabled": false
    },
    "public.unidades_medida": {
      "name": "unidades_medida",
      "schema": "",
      "columns": {
        "id": {
          "name": "id",
          "type": "integer",
          "primaryKey": true,
          "notNull": true,
          "identity": {
            "type": "always",
            "name": "unidades_medida_id_seq",
            "schema": "public",
            "increment": "1",
            "startWith": "1",
            "minValue": "1",
            "maxValue": "2147483647",
            "cache": "1",
            "cycle": false
          }
        },
        "unidad_medida": {
          "name": "unidad_medida",
          "type": "text",
          "primaryKey": false,
          "notNull": true
        }
      },
      "indexes": {},
      "foreignKeys": {},
      "compositePrimaryKeys": {},
      "uniqueConstraints": {},
      "policies": {},
      "checkConstraints": {},
      "isRLSEnabled": false
    },
    "public.usuarios": {
      "name": "usuarios",
      "schema": "",
      "columns": {
        "id": {
          "name": "id",
          "type": "integer",
          "primaryKey": true,
          "notNull": true,
          "identity": {
            "type": "always",
            "name": "usuarios_id_seq",
            "schema": "public",
            "increment": "1",
            "startWith": "1",
            "minValue": "1",
            "maxValue": "2147483647",
            "cache": "1",
            "cycle": false
          }
        },
        "nombre": {
          "name": "nombre",
          "type": "text",
          "primaryKey": false,
          "notNull": true
        },
        "apellido": {
          "name": "apellido",
          "type": "text",
          "primaryKey": false,
          "notNull": true
        },
        "correo": {
          "name": "correo",
          "type": "text",
          "primaryKey": false,
          "notNull": true
        },
        "password": {
          "name": "password",
          "type": "text",
          "primaryKey": false,
          "notNull": true
        },
        "rol": {
          "name": "rol",
          "type": "text",
          "primaryKey": false,
          "notNull": true
        },
        "activo": {
          "name": "activo",
          "type": "boolean",
          "primaryKey": false,
          "notNull": true
        }
      },
      "indexes": {},
      "foreignKeys": {},
      "compositePrimaryKeys": {},
      "uniqueConstraints": {},
      "policies": {},
      "checkConstraints": {},
      "isRLSEnabled": false
    }
  },
  "enums": {},
  "schemas": {},
  "sequences": {},
  "roles": {},
  "policies": {},
  "views": {},
  "_meta": {
    "columns": {},
    "schemas": {},
    "tables": {}
  }
}